typytypy/__init__.py
typytypy/core.py
typytypy/exceptions.py
typytypy/py.typed
typytypy-0.1.0.dist-info/METADATA
typytypy-0.1.0.dist-info/WHEEL
typytypy-0.1.0.dist-info/licenses/LICENSE
typytypy-0.1.0.dist-info/RECORD
