Metadata-Version: 2.4
Name: typytypy
Version: 0.1.0
Summary: A Bespoke Character-by-Character Text Printer.
Project-URL: Homepage, https://github.com/VDundDB/typytypy-py
Project-URL: Documentation, https://VDundDB.github.io/typytypy-py
Project-URL: Repository, https://github.com/VDundDB/typytypy-py
Project-URL: PyPI, https://pypi.org/project/typytypy
Project-URL: Issues, https://github.com/VDundDB/typytypy-py/issues
Project-URL: Changelog, https://github.com/VDundDB/typytypy-py/blob/main/CHANGELOG.md
Author: KitscherEins
Maintainer: KitscherEins
License-Expression: Apache-2.0
License-File: LICENSE
Keywords: API,animation,application,character personality,configurable,console,custom,kitschcode,output,presets,printing,profile,real-time,realistic,simulation,terminal,text,timing,typewriter,typing
Classifier: Development Status :: 4 - Beta
Classifier: Intended Audience :: Developers
Classifier: License :: OSI Approved :: Apache Software License
Classifier: Operating System :: OS Independent
Classifier: Programming Language :: Python :: 3.10
Classifier: Programming Language :: Python :: 3.11
Classifier: Programming Language :: Python :: 3.12
Classifier: Programming Language :: Python :: 3.13
Classifier: Topic :: Artistic Software
Classifier: Topic :: Documentation
Classifier: Topic :: Printing
Classifier: Topic :: Software Development :: Libraries :: Python Modules
Classifier: Topic :: System :: Console Fonts
Classifier: Topic :: Terminals
Classifier: Topic :: Text Processing
Classifier: Typing :: Typed
Requires-Python: >=3.10
Provides-Extra: dev
Requires-Dist: black>=25.9.0; extra == 'dev'
Requires-Dist: furo>=2025.9.25; extra == 'dev'
Requires-Dist: mypy>=1.18.2; extra == 'dev'
Requires-Dist: myst-parser>=4.0.1; extra == 'dev'
Requires-Dist: pytest-cov>=7.0.0; extra == 'dev'
Requires-Dist: pytest>=8.4.2; extra == 'dev'
Requires-Dist: ruff>=0.14.0; extra == 'dev'
Requires-Dist: sphinx-autobuild>=2025.8.25; extra == 'dev'
Requires-Dist: sphinx-copybutton>=0.5.2; extra == 'dev'
Requires-Dist: sphinx-design>=0.6.1; extra == 'dev'
Requires-Dist: sphinx-togglebutton>=0.3.2; extra == 'dev'
Requires-Dist: sphinx>=8.2.3; extra == 'dev'
Requires-Dist: vermin>=1.6.0; extra == 'dev'
Provides-Extra: docs
Requires-Dist: furo>=2025.9.25; extra == 'docs'
Requires-Dist: myst-parser>=4.0.1; extra == 'docs'
Requires-Dist: sphinx-autobuild>=2025.8.25; extra == 'docs'
Requires-Dist: sphinx-copybutton>=0.5.2; extra == 'docs'
Requires-Dist: sphinx-design>=0.6.1; extra == 'docs'
Requires-Dist: sphinx-togglebutton>=0.3.2; extra == 'docs'
Requires-Dist: sphinx>=8.2.3; extra == 'docs'
Provides-Extra: test
Requires-Dist: pytest-cov>=7.0.0; extra == 'test'
Requires-Dist: pytest>=8.4.2; extra == 'test'
